{"Result":true,"ErrorCode":0,"Response":{"hotelInfo":{"basic":{"label":["开业：2020","客房数：24","联系方式：18855950555"],"description":"黄山筠庭轻奢度假民宿位于黄山风景区汤口镇南大门，紧临新国线南大门东岭换乘点。","name":"黄山筠庭轻奢度假民宿","image":["//ak-d.tripcdn.com/images/200e1g000001hjsfm48C1_R_800_525.jpg"],"badge":"23","badgeHover":"携程紧密合作酒店/供应商，为携程会员提供优惠房价。","descriptionPre":"开业：2020","certiInfo":{"picUrls":["http://dimg04.c-ctrip.com/images/02044120009cie4fuA4AE_Z_702_0_Q70.jpg","http://dimg04.c-ctrip.com/images/020171200093fb9r6283D_Z_702_0_Q70.jpg","http://dimg04.c-ctrip.com/images/0201i1200093fb6m8D374_Z_702_0_Q70.jpg"],"groupPicUrls":[{"title":"平台资质","picUrls":["http://dimg04.c-ctrip.com/images/02044120009cie4fuA4AE_Z_702_0_Q70.jpg","http://dimg04.c-ctrip.com/images/020171200093fb9r6283D_Z_702_0_Q70.jpg","http://dimg04.c-ctrip.com/images/0201i1200093fb6m8D374_Z_702_0_Q70.jpg"]}]}},"detail":[{"content":"人们远离都市，来到青山绿水之间，住进各具风情和地方特色的民宿中，观景之后，还可以在民宿中尽情地感受当地人的日常生活。下榻筠庭民宿酒店，完善的设施可让您在住宿期间更加愉悦，工作人员秉承顾客至上的服务理念，为您提供宾至如归的入住感受。房间基本以原木为主，北欧风格，适合年轻人居住。客房内必需品一应俱全，住宿内设多种休闲娱乐设施，确保舒适的入住感受。 工作人员热情的服务与优美的环境完美地结合，可让您的黄山之行变得更加难忘。","image":[]}]},"hotelPolicy":{"date":{"title":"入住及退房","content":[{"title":"入住时间","description":"入住时间： 12:00后","transkey":""},{"title":"退房时间","description":"退房时间： 12:00前","transkey":""}]},"beds":{"title":"儿童及加床","description":"酒店允许客人携带儿童入住。","menu":[{"title":"使用现有床铺","description":["每房间可有1名17岁或以下的儿童使用现有床铺。"],"details":[{"title":"17岁或以下的儿童","content":[{"title":"费用","content":"使用现有床铺免费","bold":true},{"title":"早餐","content":"不包括","bold":false}]}]},{"title":"加床：","description":["不可加床"],"details":[]}]},"dining":{"title":"早餐","description":"","content":[{"title":"早餐类型","description":"中式"},{"title":"菜单类型","description":"单点"},{"title":"营业时间","description":"06:00-08:30 [星期一 - 星期日]"}],"addBreakfastDesc":"不包括早餐","isProvide":true,"addBreakfastHover":"酒店提供早餐，可到店加购选择。"},"parking":{"title":"停车场","content":["无需预约：酒店内提供私人停车场（免费）","提供充电车位。","酒店内提供标准充电站"]},"pets":{"title":"宠物","description":"不可携带宠物。"},"credit":{"title":"到店付款方式","description":"酒店接受以下付款方式","support":[{"name":"国内发行银联卡","type":"unionpay"},{"name":"微信支付","type":"wechat"},{"name":"支付宝支付","type":"alipay"},{"name":"现金支付","type":""}]},"checkInWay":{"title":"入住方式","content":["请到前台领取钥匙/门卡"]},"ageLimit":{"title":"年龄限制","description":"不允许18岁以下单独办理入住"},"specialConcern":{"title":"入住提示","description":"住宿提供方支持中国（含港澳台）及外国客人入住"}},"hotelUsefulInfo":[{"title":"酒店提示","type":"note","content":[{"facilityDescTitle":"防疫期间，根据酒店通知，来自或途径中高风险区域人群入住时要求客人提供48小时内核酸检测证明，下单之前与酒店确认接待政策，以免耽误行程！"}]}],"hotelFacility":[{"type":"popular","title":"热门设施","content":[{"facilityDesc":"接机服务","id":"105","imgList":[],"chargeType":1,"icon":"ic_new_fa_pickup","value":1},{"facilityDesc":"棋牌室","id":"24","imgList":[],"chargeType":2,"icon":"ic_new_fa_check","value":1},{"facilityDesc":"24小时大堂经理","id":"165","imgList":[],"chargeType":2,"icon":"ic_new_fa_check","value":1},{"facilityDesc":"会议厅","id":"6","imgList":["//ak-d.tripcdn.com/images/200i1g000001hevwj0171_R_800_525.jpg","//ak-d.tripcdn.com/images/0203b120008s9b0fq5E7C_R_800_525.jpg","//ak-d.tripcdn.com/images/0202u120008s96gsy392D_R_800_525.jpg"],"chargeType":1,"icon":"ic_new_fa_business","value":1},{"facilityDesc":"智能门锁","id":"310","imgList":[],"chargeType":2,"icon":"ic_new_fa_check","value":1},{"facilityDesc":"空调","id":"107","imgList":[],"chargeType":0,"icon":"ic_new_fa_check","value":1}]},{"type":"general","title":"交通服务","content":[{"facilityDesc":"送机服务","id":"361","imgList":[],"chargeType":1,"icon":"ic_new_fa_check","value":1},{"facilityDesc":"接机服务","id":"105","imgList":[],"chargeType":1,"icon":"ic_new_fa_pickup","value":1},{"facilityDesc":"接站服务","id":"263","imgList":[],"chargeType":0,"icon":"ic_new_fa_check","value":1},{"facilityDesc":"送站服务","id":"369","imgList":[],"chargeType":0,"icon":"ic_new_fa_check","value":1},{"facilityDesc":"租车服务","id":"123","imgList":[],"chargeType":2,"icon":"ic_new_bu_carreantal","value":1}]},{"type":"","title":"娱乐活动设施","content":[{"facilityDesc":"棋牌室","id":"24","imgList":[],"chargeType":2,"icon":"ic_new_fa_check","value":1},{"facilityDesc":"茶室","id":"63","imgList":[],"chargeType":2,"icon":"ic_new_fa_tea","value":1},{"facilityDesc":"投影设备","id":"349","imgList":[],"chargeType":2,"icon":"ic_new_fa_check","value":1}]},{"type":"","title":"康体设施","content":[]},{"type":"accessibility","title":"前台服务","content":[{"facilityDesc":"专职行李员","id":"96","imgList":[],"chargeType":2,"icon":"ic_new_fa_check","value":1},{"facilityDesc":"行李寄存","id":"97","imgList":[],"chargeType":0,"icon":"ic_new_fa_baggage","value":1},{"facilityDesc":"前台贵重物品保险柜","id":"95","imgList":[],"chargeType":2,"icon":"ic_new_fa_check","value":1},{"facilityDesc":"代客泊车","id":"149","imgList":[],"chargeType":0,"icon":"ic_new_fa_check","value":1},{"facilityDesc":"24小时大堂经理","id":"165","imgList":[],"chargeType":2,"icon":"ic_new_fa_check","value":1},{"facilityDesc":"叫车服务","id":"55","imgList":[],"chargeType":2,"icon":"ic_new_fa_check","value":1},{"facilityDesc":"旅游票务服务","id":"12","imgList":[],"chargeType":2,"icon":"ic_new_fa_polyglot","value":1},{"facilityDesc":"叫醒服务","id":"98","imgList":[],"chargeType":2,"icon":"ic_new_fa_wake_up","value":1},{"facilityDesc":"信用卡结算服务","id":"162","imgList":[],"chargeType":2,"icon":"ic_new_fa_check","value":1},{"facilityDesc":"快速入住退房","id":"143","imgList":[],"chargeType":2,"icon":"ic_new_fa_check","value":1},{"facilityDesc":"储物柜","id":"360","imgList":[],"chargeType":2,"icon":"ic_new_fa_check","value":1},{"facilityDesc":"24小时中文服务","id":"414","imgList":[],"chargeType":2,"icon":"ic_new_fa_check","value":1},{"facilityDesc":"24小时前台","id":"140","imgList":[],"chargeType":2,"icon":"ic_new_fa_24h_service","value":1},{"facilityDesc":"旅游交通图","id":"441","imgList":[],"chargeType":2,"icon":"ic_new_fa_check","value":1},{"facilityDesc":"邮政服务","id":"69","imgList":[],"chargeType":2,"icon":"ic_new_fa_check","value":1},{"facilityDesc":"一次性结账","id":"163","imgList":[],"chargeType":2,"icon":"ic_new_fa_check","value":1}]},{"type":"","title":"清洁服务","content":[{"facilityDesc":"打扫工具","id":"348","imgList":[],"chargeType":2,"icon":"ic_new_fa_check","value":1},{"facilityDesc":"卫生1客1扫","id":"335","imgList":[],"chargeType":2,"icon":"ic_new_fa_check","value":1},{"facilityDesc":"毛巾1客1换","id":"337","imgList":[],"chargeType":2,"icon":"ic_new_fa_check","value":1},{"facilityDesc":"牙具1客1换","id":"339","imgList":[],"chargeType":2,"icon":"ic_new_fa_check","value":1},{"facilityDesc":"被单1客1换","id":"341","imgList":[],"chargeType":2,"icon":"ic_new_fa_check","value":1},{"facilityDesc":"洗衣服务","id":"15","imgList":[],"chargeType":2,"icon":"ic_new_fa_access","value":1},{"facilityDesc":"熨斗/挂烫机","id":"356","imgList":[],"chargeType":2,"icon":"ic_new_fa_check","value":1}]},{"type":"multilingual","title":"餐饮服务","content":[{"facilityDesc":"中餐厅","id":"1","imgList":[],"chargeType":2,"icon":"ic_new_fa_shuttle_bus","value":1},{"facilityDesc":"餐厅","id":"147","imgList":["//ak-d.tripcdn.com/images/20091g000001hjg1e9708_R_800_525.jpg","//ak-d.tripcdn.com/images/200h1g000001him5u44C2_R_800_525.jpg","//ak-d.tripcdn.com/images/200l1g000001hh7k84F93_R_800_525.jpg","//ak-d.tripcdn.com/images/200g1g000001hhqfn2B65_R_800_525.jpg"],"chargeType":2,"icon":"ic_new_fa_breakfast","value":1},{"facilityDesc":"送餐服务","id":"16","imgList":[],"chargeType":2,"icon":"ic_new_fa_check","value":1}]},{"type":"sf","title":"其他服务","content":[{"facilityDesc":"管家服务","id":"139","imgList":[],"chargeType":2,"icon":"ic_new_fa_check","value":1}]},{"type":"public","title":"公共区","content":[{"facilityDesc":"公用区wifi","id":"102","imgList":[],"chargeType":2,"icon":"ic_new_fa_wifi","value":1},{"facilityDesc":"商场","id":"35","imgList":[],"chargeType":2,"icon":"ic_new_fa_check","value":1},{"facilityDesc":"非经营性客人休息区","id":"171","imgList":[],"chargeType":2,"icon":"ic_new_fa_check","value":1},{"facilityDesc":"共用厨房","id":"359","imgList":[],"chargeType":2,"icon":"ic_new_fa_check","value":1},{"facilityDesc":"礼品廊","id":"161","imgList":[],"chargeType":2,"icon":"ic_new_fa_check","value":1}]},{"type":"","title":"商务服务","content":[{"facilityDesc":"会议厅","id":"6","imgList":["//ak-d.tripcdn.com/images/200i1g000001hevwj0171_R_800_525.jpg","//ak-d.tripcdn.com/images/0203b120008s9b0fq5E7C_R_800_525.jpg","//ak-d.tripcdn.com/images/0202u120008s96gsy392D_R_800_525.jpg"],"chargeType":1,"icon":"ic_new_fa_business","value":1},{"facilityDesc":"商务服务","id":"168","imgList":[],"chargeType":2,"icon":"businessservic","value":1}]},{"type":"spa","title":"通用设施","content":[{"facilityDesc":"暖气","id":"144","imgList":[],"chargeType":2,"icon":"ic_new_fa_check","value":1},{"facilityDesc":"电梯","id":"110","imgList":[],"chargeType":2,"icon":"ic_new_fa_check","value":1},{"facilityDesc":"行政楼层","id":"174","imgList":[],"chargeType":2,"icon":"ic_new_fa_floor","value":1},{"facilityDesc":"大堂吧","id":"106","imgList":[],"chargeType":2,"icon":"ic_new_fa_check","value":1},{"facilityDesc":"公共音响系统","id":"170","imgList":[],"chargeType":2,"icon":"ic_new_fa_check","value":1},{"facilityDesc":"吸烟区","id":"142","imgList":[],"chargeType":2,"icon":"ic_new_fa_smoking","value":1},{"facilityDesc":"大堂报纸","id":"442","imgList":[],"chargeType":2,"icon":"ic_new_fa_check","value":1},{"facilityDesc":"公共区域禁烟","id":"141","imgList":[],"chargeType":2,"icon":"ic_new_fa_check","value":1},{"facilityDesc":"全部客房禁烟","id":"486","imgList":[],"chargeType":2,"icon":"ic_new_fa_check","value":1},{"facilityDesc":"无烟楼层","id":"173","imgList":[],"chargeType":2,"icon":"ic_new_fa_no_smoking","value":1},{"facilityDesc":"公共区域闭路电视监控系统","id":"177","imgList":[],"chargeType":2,"icon":"ic_new_fa_check","value":1},{"facilityDesc":"安全报警器","id":"372","imgList":[],"chargeType":2,"icon":"ic_new_fa_check","value":1},{"facilityDesc":"火灾报警器","id":"347","imgList":[],"chargeType":2,"icon":"ic_new_fa_check","value":1},{"facilityDesc":"灭火器","id":"353","imgList":[],"chargeType":2,"icon":"ic_new_fa_check","value":1},{"facilityDesc":"烟雾报警器","id":"371","imgList":[],"chargeType":2,"icon":"ic_new_fa_check","value":1}]},{"type":"dining","title":"儿童设施","content":[{"facilityDesc":"儿童牙刷","id":"333","imgList":[],"chargeType":2,"icon":"ic_new_fa_check","value":1},{"facilityDesc":"儿童拖鞋","id":"331","imgList":[],"chargeType":2,"icon":"ic_new_fa_check","value":1}]}],"hotelFacilityPage":[{"facilityDesc":"接机服务","id":"105"},{"facilityDesc":"棋牌室","id":"24"},{"facilityDesc":"24小时大堂经理","id":"165"},{"facilityDesc":"会议厅","id":"6"},{"facilityDesc":"智能门锁","id":"310"},{"facilityDesc":"空调","id":"107"}],"reservationNoticeTipsInfo":[{"title":"重要通知","application":"1","category":"1","object":"1","index":"0","itemList":[{"content":"防疫期间，根据酒店通知，来自或途径中高风险区域人群入住时要求客人提供48小时内核酸检测证明，下单之前与酒店确认接待政策，以免耽误行程！(提示有效期2021/12/15起)"}]}]}}