{"Result":true,"ErrorCode":0,"Response":{"hotelInfo":{"basic":{"label":["开业：2018","装修时间：2018","客房数：39","联系方式：17355951656"],"description":"老街深巷铺连肩，密雨重帘古画延。","name":"黄山开元颐居·还淳屯溪老街店(精品民宿)","image":["//ak-d.tripcdn.com/images/200j1a0000018xq978078_R_800_525.jpg"],"badge":"24","badgeHover":"携程战略合作酒店/供应商，拥有优质服务、优良品质及优惠房价。","descriptionPre":"开业：2018","certiInfo":{"picUrls":["http://dimg04.c-ctrip.com/images/02044120009cie4fuA4AE_Z_702_0_Q70.jpg","http://dimg04.c-ctrip.com/images/020171200093fb9r6283D_Z_702_0_Q70.jpg","http://dimg04.c-ctrip.com/images/0201i1200093fb6m8D374_Z_702_0_Q70.jpg"],"groupPicUrls":[{"title":"平台资质","picUrls":["http://dimg04.c-ctrip.com/images/02044120009cie4fuA4AE_Z_702_0_Q70.jpg","http://dimg04.c-ctrip.com/images/020171200093fb9r6283D_Z_702_0_Q70.jpg","http://dimg04.c-ctrip.com/images/0201i1200093fb6m8D374_Z_702_0_Q70.jpg"]}]}},"detail":[{"content":"黛瓦马头藏密语，徽商儒影透微烟。","image":[]},{"content":"在有“流动的清明上河图”美誉的安徽黄山屯溪老街内，民宿隐匿于此。九栋老宅，五大主题，集合成一片拥有39间房的徽州儒商生活文化民宿集群，徽州人的茶、盐、木、当四大徽商文化和一大生活文化“火”，在这处徽商民宿集群里得以淋漓尽致的呈现。“茶院”以茶陶情，“盐院”藏富不露，“木院”繁华重现，“当院”如数家珍，“火院”知足常乐。徽州的文化，江南的底蕴，老街人家的烟火味儿，又和着些书香茶舍、咖香墨韵、徽式小厨的文艺小情调和对隐居世外生活的些许向往，在这里新旧穿越，水墨纵横。集群内所有客房均配备独立的供暖系统、数字电视、开元天逸之床睡眠系统，无线网络覆盖酒店整体区域。私人定制款的早餐，满足您的味蕾，填满您空荡的肠胃，美好的一天，让您从丰盛而健康的早餐开始。","image":[]},{"content":"无奢华但大气，无清高却雅致。十栋老宅，依旧时原貌改建，或层楼叠院、高脊飞檐，或曲径回廊、亭台楼榭，徽式的天井里，亦可以晨沐朝霞、夜观星斗，还原当年老街徽商的生活场景。入住这里，可出得繁华，感受一方砖一方砖的徽商路，可入得清净，远离喧嚣，修篱种菊。进门了，有管家奉上一杯桃花欢迎茶，临去了，衣带也飘着余香；正是老舍笔下：“小华山下桃花水，况有茶香与墨香”的美好生活写照。","image":[]}]},"hotelPolicy":{"date":{"title":"入住及退房","content":[{"title":"入住时间","description":"入住时间： 14:00后","transkey":""},{"title":"退房时间","description":"退房时间： 12:00前","transkey":""}]},"beds":{"title":"儿童及加床","description":"酒店允许客人携带儿童入住。","menu":[{"title":"使用现有床铺","description":["每房间可有1名17岁或以下的儿童使用现有床铺。"],"details":[{"title":"17岁或以下的儿童","content":[{"title":"费用","content":"使用现有床铺免费","bold":true},{"title":"早餐","content":"不包括","bold":false}]}]},{"title":"加床：","description":["不可加床"],"details":[]},{"title":"备注","description":["加床政策、儿童政策会根据客房类型而有所不同，房价仅适用于特定数量的客人。携带儿童与额外客人可能会产生额外费用，详情请咨询酒店。"],"details":[]}]},"dining":{"title":"早餐","description":"","content":[{"title":"早餐类型","description":"中式"},{"title":"费用","description":"{0}￥68.00{/0} 每位"},{"title":"营业时间","description":"07:00-10:00 [星期一 - 星期日]"}],"addBreakfastDesc":"不包括早餐","isProvide":true,"addBreakfastHover":"酒店提供早餐，可到店加购选择。"},"parking":{"title":"停车场","content":["需预约：酒店附近提供公共停车场"]},"pets":{"title":"宠物","description":"不可携带宠物。"},"credit":{"title":"到店付款方式","description":"酒店接受以下付款方式","support":[{"name":"万事达(Master)","type":"mastercard"},{"name":"威士(VISA)","type":"visa"},{"name":"JCB","type":"jcb"},{"name":"国内发行银联卡","type":"unionpay"},{"name":"微信支付","type":"wechat"},{"name":"支付宝支付","type":"alipay"}]},"ageLimit":{"title":"年龄限制","description":"不允许18岁以下单独办理入住"},"specialConcern":{"title":"入住提示","description":"住宿提供方支持中国（含港澳台）及外国客人入住"}},"hotelUsefulInfo":[{"title":"酒店提示","type":"note","content":[{"facilityDescTitle":"防疫期间，根据酒店通知，办理入住需提供本地48小时内核酸检测证明，请在下单前与酒店确认接待政策，以免影响您的入住"}]}],"hotelFacility":[{"type":"popular","title":"热门设施","content":[{"facilityDesc":"接机服务","id":"105","imgList":[],"chargeType":0,"icon":"ic_new_fa_pickup","value":1},{"facilityDesc":"24小时前台","id":"140","imgList":[],"chargeType":2,"icon":"ic_new_fa_24h_service","value":1},{"facilityDesc":"会议厅","id":"6","imgList":["//ak-d.tripcdn.com/images/200q14000000wj3avD659_R_800_525.jpg","//ak-d.tripcdn.com/images/200t1a00000191ijl9307_R_800_525.jpg"],"chargeType":2,"icon":"ic_new_fa_business","value":1},{"facilityDesc":"棋牌室","id":"24","imgList":[],"chargeType":2,"icon":"ic_new_fa_check","value":1},{"facilityDesc":"智能门锁","id":"310","imgList":[],"chargeType":2,"icon":"ic_new_fa_check","value":1},{"facilityDesc":"空调","id":"107","imgList":[],"chargeType":0,"icon":"ic_new_fa_check","value":1}]},{"type":"general","title":"交通服务","content":[{"facilityDesc":"送机服务","id":"361","imgList":[],"chargeType":0,"icon":"ic_new_fa_check","value":1},{"facilityDesc":"接机服务","id":"105","imgList":[],"chargeType":0,"icon":"ic_new_fa_pickup","value":1},{"facilityDesc":"接站服务","id":"263","imgList":[],"chargeType":0,"icon":"ic_new_fa_check","value":1},{"facilityDesc":"送站服务","id":"369","imgList":[],"chargeType":0,"icon":"ic_new_fa_check","value":1},{"facilityDesc":"租车服务","id":"123","imgList":[],"chargeType":2,"icon":"ic_new_bu_carreantal","value":1}]},{"type":"","title":"娱乐活动设施","content":[{"facilityDesc":"室外泳池","id":"61","imgList":["//ak-d.tripcdn.com/images/0206k120008r1ulb3B76B_R_800_525.jpg"],"chargeType":0,"icon":"ic_new_fa_swimming","value":1},{"facilityDesc":"儿童泳池","id":"435","imgList":[],"chargeType":2,"icon":"ic_new_fa_check","value":1},{"facilityDesc":"棋牌室","id":"24","imgList":[],"chargeType":2,"icon":"ic_new_fa_check","value":1},{"facilityDesc":"茶室","id":"63","imgList":[],"chargeType":2,"icon":"ic_new_fa_tea","value":1},{"facilityDesc":"投影设备","id":"349","imgList":[],"chargeType":2,"icon":"ic_new_fa_check","value":1}]},{"type":"","title":"康体设施","content":[]},{"type":"accessibility","title":"前台服务","content":[{"facilityDesc":"会员专属通道","id":"529","imgList":[],"chargeType":2,"icon":"ic_new_fa_check","value":1},{"facilityDesc":"行李寄存","id":"97","imgList":[],"chargeType":0,"icon":"ic_new_fa_baggage","value":1},{"facilityDesc":"代客泊车","id":"149","imgList":[],"chargeType":2,"icon":"ic_new_fa_check","value":1},{"facilityDesc":"部分时段大堂经理","id":"166","imgList":[],"chargeType":2,"icon":"ic_new_fa_check","value":1},{"facilityDesc":"礼宾服务","id":"127","imgList":[],"chargeType":2,"icon":"ic_new_fa_check","value":1},{"facilityDesc":"旅游票务服务","id":"12","imgList":[],"chargeType":2,"icon":"ic_new_fa_polyglot","value":1},{"facilityDesc":"叫醒服务","id":"98","imgList":[],"chargeType":2,"icon":"ic_new_fa_wake_up","value":1},{"facilityDesc":"信用卡结算服务","id":"162","imgList":[],"chargeType":2,"icon":"ic_new_fa_check","value":1},{"facilityDesc":"快速入住退房","id":"143","imgList":[],"chargeType":2,"icon":"ic_new_fa_check","value":1},{"facilityDesc":"24小时前台","id":"140","imgList":[],"chargeType":2,"icon":"ic_new_fa_24h_service","value":1},{"facilityDesc":"旅游交通图","id":"441","imgList":[],"chargeType":2,"icon":"ic_new_fa_check","value":1},{"facilityDesc":"邮政服务","id":"69","imgList":[],"chargeType":2,"icon":"ic_new_fa_check","value":1},{"facilityDesc":"一次性结账","id":"163","imgList":[],"chargeType":2,"icon":"ic_new_fa_check","value":1}]},{"type":"","title":"清洁服务","content":[{"facilityDesc":"卫生1客1扫","id":"335","imgList":[],"chargeType":2,"icon":"ic_new_fa_check","value":1},{"facilityDesc":"毛巾1客1换","id":"337","imgList":[],"chargeType":2,"icon":"ic_new_fa_check","value":1},{"facilityDesc":"牙具1客1换","id":"339","imgList":[],"chargeType":2,"icon":"ic_new_fa_check","value":1},{"facilityDesc":"被单1客1换","id":"341","imgList":[],"chargeType":2,"icon":"ic_new_fa_check","value":1},{"facilityDesc":"外送洗衣服务","id":"178","imgList":[],"chargeType":2,"icon":"ic_new_fa_check","value":1}]},{"type":"multilingual","title":"餐饮服务","content":[{"facilityDesc":"中餐厅","id":"1","imgList":[],"chargeType":2,"icon":"ic_new_fa_shuttle_bus","value":1},{"facilityDesc":"餐厅","id":"147","imgList":["//ak-d.tripcdn.com/images/20041a0000018x7l2CE9E_R_800_525.jpg","//ak-d.tripcdn.com/images/200a1a0000018zju4A19A_R_800_525.jpg","//ak-d.tripcdn.com/images/200r1900000169w0i8267_R_800_525.jpg","//ak-d.tripcdn.com/images/0AD6m120008nm2hkc71A3_R_800_525.jpg","//ak-d.tripcdn.com/images/0AD6k120008nm22bc412B_R_800_525.jpg","//ak-d.tripcdn.com/images/0AD39120008nm2zm3CA64_R_800_525.jpg","//ak-d.tripcdn.com/images/0AD0d120008nm1m459641_R_800_525.jpg","//ak-d.tripcdn.com/images/0AD5z120008nm220xAA15_R_800_525.jpg","//ak-d.tripcdn.com/images/0AD0d120008nm22bdADF9_R_800_525.jpg","//ak-d.tripcdn.com/images/20091a00000190mrc27AB_R_800_525.jpg","//ak-d.tripcdn.com/images/20061a0000018yumm8F8D_R_800_525.jpg"],"chargeType":2,"icon":"ic_new_fa_breakfast","value":1},{"facilityDesc":"儿童餐","id":"330","imgList":[],"chargeType":2,"icon":"ic_new_fa_child","value":1}]},{"type":"sf","title":"其他服务","content":[{"facilityDesc":"管家服务","id":"139","imgList":[],"chargeType":2,"icon":"ic_new_fa_check","value":1},{"facilityDesc":"多语种服务","id":"138","imgList":[],"chargeType":2,"icon":"ic_new_fa_polyglot","value":1},{"facilityDesc":"急救包","id":"344","imgList":[],"chargeType":2,"icon":"ic_new_fa_check","value":1},{"facilityDesc":"保安人员","id":"479","imgList":[],"chargeType":2,"icon":"ic_new_fa_check","value":1}]},{"type":"public","title":"公共区","content":[{"facilityDesc":"公用区wifi","id":"102","imgList":[],"chargeType":0,"icon":"ic_new_fa_wifi","value":1},{"facilityDesc":"非经营性客人休息区","id":"171","imgList":[],"chargeType":2,"icon":"ic_new_fa_check","value":1},{"facilityDesc":"游戏室","id":"154","imgList":[],"chargeType":2,"icon":"ic_new_fa_check","value":1},{"facilityDesc":"户外家具","id":"385","imgList":[],"chargeType":2,"icon":"ic_new_fa_check","value":1}]},{"type":"","title":"商务服务","content":[{"facilityDesc":"会议厅","id":"6","imgList":["//ak-d.tripcdn.com/images/200q14000000wj3avD659_R_800_525.jpg","//ak-d.tripcdn.com/images/200t1a00000191ijl9307_R_800_525.jpg"],"chargeType":2,"icon":"ic_new_fa_business","value":1},{"facilityDesc":"商务中心","id":"8","imgList":[],"chargeType":2,"icon":"ic_new_fa_businesscenter","value":1},{"facilityDesc":"多媒体演示系统","id":"176","imgList":[],"chargeType":2,"icon":"ic_new_fa_media","value":1},{"facilityDesc":"多功能厅","id":"164","imgList":[],"chargeType":2,"icon":"ic_new_fa_multimedia","value":1}]},{"type":"spa","title":"通用设施","content":[{"facilityDesc":"加湿器","id":"354","imgList":[],"chargeType":2,"icon":"ic_new_fa_check","value":1},{"facilityDesc":"电梯","id":"110","imgList":[],"chargeType":2,"icon":"ic_new_fa_check","value":0},{"facilityDesc":"大堂吧","id":"106","imgList":[],"chargeType":2,"icon":"ic_new_fa_check","value":1},{"facilityDesc":"公共音响系统","id":"170","imgList":[],"chargeType":2,"icon":"ic_new_fa_check","value":1},{"facilityDesc":"吸烟区","id":"142","imgList":[],"chargeType":2,"icon":"ic_new_fa_smoking","value":1},{"facilityDesc":"大堂报纸","id":"442","imgList":[],"chargeType":2,"icon":"ic_new_fa_check","value":1},{"facilityDesc":"公共区域禁烟","id":"141","imgList":[],"chargeType":2,"icon":"ic_new_fa_check","value":1},{"facilityDesc":"全部客房禁烟","id":"486","imgList":[],"chargeType":2,"icon":"ic_new_fa_check","value":1},{"facilityDesc":"无烟楼层","id":"173","imgList":[],"chargeType":2,"icon":"ic_new_fa_no_smoking","value":1},{"facilityDesc":"公共区域闭路电视监控系统","id":"177","imgList":[],"chargeType":2,"icon":"ic_new_fa_check","value":1},{"facilityDesc":"火灾报警器","id":"347","imgList":[],"chargeType":2,"icon":"ic_new_fa_check","value":1},{"facilityDesc":"门禁系统","id":"350","imgList":[],"chargeType":2,"icon":"ic_new_fa_check","value":1},{"facilityDesc":"灭火器","id":"353","imgList":[],"chargeType":2,"icon":"ic_new_fa_check","value":1},{"facilityDesc":"新风系统","id":"351","imgList":[],"chargeType":2,"icon":"ic_new_fa_check","value":1},{"facilityDesc":"烟雾报警器","id":"371","imgList":[],"chargeType":2,"icon":"ic_new_fa_check","value":1}]},{"type":"dining","title":"儿童设施","content":[{"facilityDesc":"儿童托管","id":"122","imgList":[],"chargeType":2,"icon":"ic_new_fa_childcaree","value":1},{"facilityDesc":"儿童玩具","id":"334","imgList":[],"chargeType":2,"icon":"ic_new_fa_check","value":1},{"facilityDesc":"儿童牙刷","id":"333","imgList":[],"chargeType":2,"icon":"ic_new_fa_check","value":1},{"facilityDesc":"儿童浴袍","id":"332","imgList":[],"chargeType":2,"icon":"ic_new_fa_check","value":1},{"facilityDesc":"儿童拖鞋","id":"331","imgList":[],"chargeType":2,"icon":"ic_new_fa_check","value":1},{"facilityDesc":"儿童书籍/影音","id":"368","imgList":[],"chargeType":2,"icon":"ic_new_fa_check","value":1}]}],"hotelFacilityPage":[{"facilityDesc":"接机服务","id":"105"},{"facilityDesc":"24小时前台","id":"140"},{"facilityDesc":"会议厅","id":"6"},{"facilityDesc":"棋牌室","id":"24"},{"facilityDesc":"智能门锁","id":"310"},{"facilityDesc":"空调","id":"107"}],"reservationNoticeTipsInfo":[{"title":"重要通知","application":"1","category":"1","object":"1","index":"0","itemList":[{"content":"防疫期间，根据酒店通知，办理入住需提供本地48小时内核酸检测证明，请在下单前与酒店确认接待政策，以免影响您的入住(提示有效期2022/03/24起)"}]}]}}